scrapbook_ext/__init__.py
scrapbook_ext-0.0.0a1.dist-info/METADATA
scrapbook_ext-0.0.0a1.dist-info/WHEEL
scrapbook_ext-0.0.0a1.dist-info/top_level.txt
scrapbook_ext-0.0.0a1.dist-info/RECORD
