Metadata-Version: 2.1
Name: scrapbook-ext
Version: 0.0.0a1
Summary: Extensions for scrapbook
Requires-Python: >=3.6
Requires-Dist: scrapbook
Provides-Extra: dev
